[
  {
    "appId": "com.mobiusx.live4dresults",
    "appPrice": 0,
    "appScore": 4.5362,
    "appTitle": "Live 4D Results ! (MY & SG)",
    "revAuthor": "Hazri mila",
    "revDate": "2017-11-01",
    "revRating": 5,
    "revText": "terbaik tp sy blm kena2 lg ni",
    "revTitle": "NA",
    "predicted": "Normal"
  },
  {
    "appId": "com.mobiusx.live4dresults",
    "appPrice": 0,
    "appScore": 4.5362,
    "appTitle": "Live 4D Results ! (MY & SG)",
    "revAuthor": "NA",
    "revDate": "2017-11-17",
    "revRating": 5,
    "revText": "ksi kna la aku ni hri plis",
    "revTitle": "NA",
    "predicted": "Normal"
  },
  {
    "appId": "com.mobiusx.live4dresults",
    "appPrice": 0,
    "appScore": 4.5362,
    "appTitle": "Live 4D Results ! (MY & SG)",
    "revAuthor": "Tan Tan",
    "revDate": "2017-11-26",
    "revRating": 5,
    "revText": "terbaik lh bgi mudah kena lg ok",
    "revTitle": "NA",
    "predicted": "Normal"
  },
  {
    "appId": "com.mobiusx.live4dresults",
    "appPrice": 0,
    "appScore": 4.5362,
    "appTitle": "Live 4D Results ! (MY & SG)",
    "revAuthor": "Along Along",
    "revDate": "2017-11-05",
    "revRating": 5,
    "revText": "aplikasi yang bgus dan mudah melihat rezaut no hihi",
    "revTitle": "NA",
    "predicted": "Normal"
  },
  {
    "appId": "com.mobiusx.live4dresults",
    "appPrice": 0,
    "appScore": 4.5362,
    "appTitle": "Live 4D Results ! (MY & SG)",
    "revAuthor": "NA",
    "revDate": "2017-11-19",
    "revRating": 5,
    "revText": "memang ada kena tapi masih dibawah terus bila mahu naik haha tak pa janji kena",
    "revTitle": "NA",
    "predicted": "Normal"
  },
  {
    "appId": "com.mobiusx.live4dresults",
    "appPrice": 0,
    "appScore": 4.5362,
    "appTitle": "Live 4D Results ! (MY & SG)",
    "revAuthor": "Zaki Hafidz",
    "revDate": "2017-12-04",
    "revRating": 5,
    "revText": "sangat susah memprediksi angka kira nasib yg nentukan",
    "revTitle": "NA",
    "predicted": "Normal"
  },
  {
    "appId": "com.mobiusx.live4dresults",
    "appPrice": 0,
    "appScore": 4.5362,
    "appTitle": "Live 4D Results ! (MY & SG)",
    "revAuthor": "dav david",
    "revDate": "2017-12-16",
    "revRating": 2,
    "revText": "bagi no x pernah kena hampeh ada la",
    "revTitle": "NA",
    "predicted": "Spam"
  },
  {
    "appId": "com.mobiusx.live4dresults",
    "appPrice": 0,
    "appScore": 4.5362,
    "appTitle": "Live 4D Results ! (MY & SG)",
    "revAuthor": "Adam Dian",
    "revDate": "2017-11-25",
    "revRating": 2,
    "revText": "bkin panas ndak prnah menag biar satu kali",
    "revTitle": "NA",
    "predicted": "Spam"
  },
  {
    "appId": "com.mobiusx.live4dresults",
    "appPrice": 0,
    "appScore": 4.5362,
    "appTitle": "Live 4D Results ! (MY & SG)",
    "revAuthor": "Michael Hudson",
    "revDate": "2017-11-22",
    "revRating": 5,
    "revText": "cepat mendapat keputusan ada no bertuah lagi  mudah dan senang",
    "revTitle": "NA",
    "predicted": "Normal"
  },
  {
    "appId": "com.mobiusx.live4dresults",
    "appPrice": 0,
    "appScore": 4.5362,
    "appTitle": "Live 4D Results ! (MY & SG)",
    "revAuthor": "Hasn Iskandar",
    "revDate": "2017-11-03",
    "revRating": 5,
    "revText": "tak pernah kena seumur hidup",
    "revTitle": "NA",
    "predicted": "Normal"
  },
  {
    "appId": "com.mobiusx.live4dresults",
    "appPrice": 0,
    "appScore": 4.5362,
    "appTitle": "Live 4D Results ! (MY & SG)",
    "revAuthor": "Benjamin Jengkin",
    "revDate": "2017-12-04",
    "revRating": 5,
    "revText": "keputusan keluar cepat harap dapat menang jackpot ini kali",
    "revTitle": "NA",
    "predicted": "Normal"
  },
  {
    "appId": "com.mobiusx.live4dresults",
    "appPrice": 0,
    "appScore": 4.5362,
    "appTitle": "Live 4D Results ! (MY & SG)",
    "revAuthor": "Jumadil Samsul",
    "revDate": "2017-10-22",
    "revRating": 5,
    "revText": "shukur lah baru download dah kenak  ada lah kalau ada hahaha",
    "revTitle": "NA",
    "predicted": "Normal"
  },
  {
    "appId": "com.mobiusx.live4dresults",
    "appPrice": 0,
    "appScore": 4.5362,
    "appTitle": "Live 4D Results ! (MY & SG)",
    "revAuthor": "Musashi Mukhtar",
    "revDate": "2017-12-06",
    "revRating": 5,
    "revText": "cume nak kate bagus je sebab tak payah beli news paper lagi thanks",
    "revTitle": "NA",
    "predicted": "Normal"
  },
  {
    "appId": "com.mobiusx.live4dresults",
    "appPrice": 0,
    "appScore": 4.5362,
    "appTitle": "Live 4D Results ! (MY & SG)",
    "revAuthor": "NA",
    "revDate": "2017-10-31",
    "revRating": 5,
    "revText": "ok juga mnatau ada nsip kena nmbor one best ooh",
    "revTitle": "NA",
    "predicted": "Normal"
  },
  {
    "appId": "com.mobiusx.live4dresults",
    "appPrice": 0,
    "appScore": 4.5362,
    "appTitle": "Live 4D Results ! (MY & SG)",
    "revAuthor": "sarutobi sensei",
    "revDate": "2017-12-05",
    "revRating": 5,
    "revText": "best app ni tapi kalau boleh pertingkat kn lagi best",
    "revTitle": "NA",
    "predicted": "Normal"
  },
  {
    "appId": "com.mobiusx.live4dresults",
    "appPrice": 0,
    "appScore": 4.5362,
    "appTitle": "Live 4D Results ! (MY & SG)",
    "revAuthor": "Bibi Lan",
    "revDate": "2017-12-06",
    "revRating": 3,
    "revText": "3 bintang jelah dlu klau da kena baru bgi 5bntang",
    "revTitle": "NA",
    "predicted": "Spam"
  },
  {
    "appId": "com.mobiusx.live4dresults",
    "appPrice": 0,
    "appScore": 4.5362,
    "appTitle": "Live 4D Results ! (MY & SG)",
    "revAuthor": "NA",
    "revDate": "2017-12-13",
    "revRating": 3,
    "revText": "lebih cepat dan tepat",
    "revTitle": "NA",
    "predicted": "Spam"
  },
  {
    "appId": "com.mobiusx.live4dresults",
    "appPrice": 0,
    "appScore": 4.5362,
    "appTitle": "Live 4D Results ! (MY & SG)",
    "revAuthor": "NA",
    "revDate": "2017-12-20",
    "revRating": 3,
    "revText": "no mimpi tidak tepat",
    "revTitle": "NA",
    "predicted": "Normal"
  },
  {
    "appId": "com.mobiusx.live4dresults",
    "appPrice": 0,
    "appScore": 4.5362,
    "appTitle": "Live 4D Results ! (MY & SG)",
    "revAuthor": "budak kampung",
    "revDate": "2017-12-10",
    "revRating": 5,
    "revText": "terbaik lah  tak payah buka google lagi nak tengok results keluar",
    "revTitle": "NA",
    "predicted": "Normal"
  },
  {
    "appId": "com.mobiusx.live4dresults",
    "appPrice": 0,
    "appScore": 4.5362,
    "appTitle": "Live 4D Results ! (MY & SG)",
    "revAuthor": "NA",
    "revDate": "2017-12-10",
    "revRating": 5,
    "revText": "versi untuk lebih lama",
    "revTitle": "NA",
    "predicted": "Normal"
  },
  {
    "appId": "com.mobiusx.live4dresults",
    "appPrice": 0,
    "appScore": 4.5362,
    "appTitle": "Live 4D Results ! (MY & SG)",
    "revAuthor": "Eddysham Resinin",
    "revDate": "2017-12-16",
    "revRating": 5,
    "revText": "ermmm  kenapa lah ni bertuah tuh selalu tak betul  tapi app memang up bugus sangat",
    "revTitle": "NA",
    "predicted": "Normal"
  },
  {
    "appId": "com.mobiusx.live4dresults",
    "appPrice": 0,
    "appScore": 4.5362,
    "appTitle": "Live 4D Results ! (MY & SG)",
    "revAuthor": "Free Ddyy",
    "revDate": "2017-12-26",
    "revRating": 5,
    "revText": "no yg di beli selalu kuar lain tmpt di beli lain plak tmpt kuar nasib badan",
    "revTitle": "NA",
    "predicted": "Normal"
  },
  {
    "appId": "com.mobiusx.live4dresults",
    "appPrice": 0,
    "appScore": 4.5362,
    "appTitle": "Live 4D Results ! (MY & SG)",
    "revAuthor": "NA",
    "revDate": "2017-10-31",
    "revRating": 5,
    "revText": "powww thenks hahaii baru je dnloud ke esuk nye tmbos thenks i like",
    "revTitle": "NA",
    "predicted": "Normal"
  },
  {
    "appId": "com.mobiusx.live4dresults",
    "appPrice": 0,
    "appScore": 4.5362,
    "appTitle": "Live 4D Results ! (MY & SG)",
    "revAuthor": "NA",
    "revDate": "2017-11-06",
    "revRating": 5,
    "revText": "sangat baik apl ne",
    "revTitle": "NA",
    "predicted": "Normal"
  },
  {
    "appId": "com.mobiusx.live4dresults",
    "appPrice": 0,
    "appScore": 4.5362,
    "appTitle": "Live 4D Results ! (MY & SG)",
    "revAuthor": "Jai Renggo",
    "revDate": "2018-01-06",
    "revRating": 2,
    "revText": "mcm cibai la bila mau kasi naik no aku 1612 bagi la no 1",
    "revTitle": "NA",
    "predicted": "Spam"
  },
  {
    "appId": "com.mobiusx.live4dresults",
    "appPrice": 0,
    "appScore": 4.5362,
    "appTitle": "Live 4D Results ! (MY & SG)",
    "revAuthor": "NA",
    "revDate": "2018-01-07",
    "revRating": 5,
    "revText": "berpuas hati dengan aplikasi ini kerana banyak sistem yg menarik untuk dimenangi",
    "revTitle": "NA",
    "predicted": "Normal"
  },
  {
    "appId": "com.mobiusx.live4dresults",
    "appPrice": 0,
    "appScore": 4.5362,
    "appTitle": "Live 4D Results ! (MY & SG)",
    "revAuthor": "NA",
    "revDate": "2017-12-30",
    "revRating": 4,
    "revText": "ckup sekadar 4 star dlu ye  dh naik no 1 nti  sy kasi up 1 star lg hehe",
    "revTitle": "NA",
    "predicted": "Normal"
  },
  {
    "appId": "com.mobiusx.live4dresults",
    "appPrice": 0,
    "appScore": 4.5362,
    "appTitle": "Live 4D Results ! (MY & SG)",
    "revAuthor": "muhammad azwar",
    "revDate": "2017-11-28",
    "revRating": 5,
    "revText": "saya suka  yessss sudah berkali kali saya kena no 1 dan yg lain lain  siapa rajin siapa kena yesssss",
    "revTitle": "NA",
    "predicted": "Normal"
  },
  {
    "appId": "com.mobiusx.live4dresults",
    "appPrice": 0,
    "appScore": 4.5362,
    "appTitle": "Live 4D Results ! (MY & SG)",
    "revAuthor": "Hans Isam",
    "revDate": "2017-12-16",
    "revRating": 5,
    "revText": "skli skli bagilh saya kena 😡",
    "revTitle": "NA",
    "predicted": "Normal"
  },
  {
    "appId": "com.mobiusx.live4dresults",
    "appPrice": 0,
    "appScore": 4.5362,
    "appTitle": "Live 4D Results ! (MY & SG)",
    "revAuthor": "Ali988 988ali",
    "revDate": "2017-12-23",
    "revRating": 5,
    "revText": "kalau kena 6d barulah cuuuun😊😁",
    "revTitle": "NA",
    "predicted": "Normal"
  },
  {
    "appId": "com.mobiusx.live4dresults",
    "appPrice": 0,
    "appScore": 4.5362,
    "appTitle": "Live 4D Results ! (MY & SG)",
    "revAuthor": "NA",
    "revDate": "2017-12-13",
    "revRating": 5,
    "revText": "apa beza beli tiket brtuah dgn beli no ekor duit kita sendiri bukan merompak pun beli no ekor mengharap menang beli tiket bertuah mgharap menang juga  beli no ekor haram  beli tiket bertuah tak pula haram  pakai duit juga tu",
    "revTitle": "NA",
    "predicted": "Normal"
  },
  {
    "appId": "com.mobiusx.live4dresults",
    "appPrice": 0,
    "appScore": 4.5362,
    "appTitle": "Live 4D Results ! (MY & SG)",
    "revAuthor": "Anis Rahmawati",
    "revDate": "2017-12-04",
    "revRating": 5,
    "revText": "3644 dpt dr nomber bertuah naik nomer 1 kat sabah tu hari thank you",
    "revTitle": "NA",
    "predicted": "Normal"
  },
  {
    "appId": "com.mobiusx.live4dresults",
    "appPrice": 0,
    "appScore": 4.5362,
    "appTitle": "Live 4D Results ! (MY & SG)",
    "revAuthor": "black empire",
    "revDate": "2017-12-30",
    "revRating": 1,
    "revText": "apa hal nombor saya tak pernah keluar",
    "revTitle": "NA",
    "predicted": "Normal"
  },
  {
    "appId": "com.mobiusx.live4dresults",
    "appPrice": 0,
    "appScore": 4.5362,
    "appTitle": "Live 4D Results ! (MY & SG)",
    "revAuthor": "mijuroh ejingka",
    "revDate": "2017-12-19",
    "revRating": 5,
    "revText": "app ni memang ok lh untuk tengok result tapi tdk ckp lh kita kana sbp tdk pernah kana no1 tapi hati kana sbr lh mana tau kana 6d haha",
    "revTitle": "NA",
    "predicted": "Normal"
  },
  {
    "appId": "com.mobiusx.live4dresults",
    "appPrice": 0,
    "appScore": 4.5362,
    "appTitle": "Live 4D Results ! (MY & SG)",
    "revAuthor": "Kim Beom",
    "revDate": "2017-11-18",
    "revRating": 5,
    "revText": "hp sya jd mangsa tu beliau mw tngk result no hahaha ",
    "revTitle": "JOELIVER",
    "predicted": "Normal"
  },
  {
    "appId": "com.mobiusx.live4dresults",
    "appPrice": 0,
    "appScore": 4.5362,
    "appTitle": "Live 4D Results ! (MY & SG)",
    "revAuthor": "NA",
    "revDate": "2017-12-09",
    "revRating": 4,
    "revText": "nombor saya naik 7550 tapi tak beli he apa nak jadi lah nasib aku nombor tak pernah kena haritu pula",
    "revTitle": "NA",
    "predicted": "Normal"
  },
  {
    "appId": "com.mobiusx.live4dresults",
    "appPrice": 0,
    "appScore": 4.5362,
    "appTitle": "Live 4D Results ! (MY & SG)",
    "revAuthor": "NA",
    "revDate": "2017-12-08",
    "revRating": 5,
    "revText": "no saya 6616 beri kena no 1 sabtu dan ahad ini",
    "revTitle": "NA",
    "predicted": "Normal"
  },
  {
    "appId": "com.mobiusx.live4dresults",
    "appPrice": 0,
    "appScore": 4.5362,
    "appTitle": "Live 4D Results ! (MY & SG)",
    "revAuthor": "NA",
    "revDate": "2017-12-06",
    "revRating": 5,
    "revText": "dh banyak kali kta ambil no brtuah kat app nie tak kna pun cubalh skali tak sabar2 nak kena bgi nombor bertuah kt saya utk hari sabtu dan ahad kita nak menang kita dh bagi 5star app ini pula bagilah 5kali utk kta menang bgi nombor 1",
    "revTitle": "NA",
    "predicted": "Normal"
  },
  {
    "appId": "com.mobiusx.live4dresults",
    "appPrice": 0,
    "appScore": 4.5362,
    "appTitle": "Live 4D Results ! (MY & SG)",
    "revAuthor": "NA",
    "revDate": "2017-12-13",
    "revRating": 5,
    "revText": "yah nasip no yg selalu ku beli tk naik 2 ya tolong lah aku dh habis2 modal ni bagi lah aku kenak no sekali saja klau aku kenak no in 4705 aku terus pulang kampung dah betahun2 ingin jumpa keluarga ku？",
    "revTitle": "NA",
    "predicted": "Normal"
  },
  {
    "appId": "com.mobiusx.live4dresults",
    "appPrice": 0,
    "appScore": 4.5362,
    "appTitle": "Live 4D Results ! (MY & SG)",
    "revAuthor": "NA",
    "revDate": "2017-12-24",
    "revRating": 2,
    "revText": "kenapa tak bagi no saya keluar habis 1 tahun saya tunggu no saya keluar saya memang benci sangat  !!! dear toto dan cash sarawak  9479 dan 5987 takde keluar di no yang tinggi  masa tak beli saya out station baru keluar  boleh check kalau 9479 dan 5987 memang tak pernah keluar  rugi betul aduhai  !!! baca lah apa kami kirim dan komen tu  jangan buat tak tahu je  !! saya ni pelanggan tetap tapi sekarang saya betul tak puas hati  hrmmm",
    "revTitle": "NA",
    "predicted": "Spam"
  },
  {
    "appId": "com.mobiusx.live4dresults",
    "appPrice": 0,
    "appScore": 4.5362,
    "appTitle": "Live 4D Results ! (MY & SG)",
    "revAuthor": "Haiqal Aiqal",
    "revDate": "2017-12-06",
    "revRating": 5,
    "revText": "entah nak cakap apa",
    "revTitle": "NA",
    "predicted": "Normal"
  },
  {
    "appId": "com.mobiusx.live4dresults",
    "appPrice": 0,
    "appScore": 4.5362,
    "appTitle": "Live 4D Results ! (MY & SG)",
    "revAuthor": "Ajai Lawin",
    "revDate": "2017-10-21",
    "revRating": 5,
    "revText": "pemberitahu untuk special race",
    "revTitle": "NA",
    "predicted": "Normal"
  },
  {
    "appId": "com.mobiusx.live4dresults",
    "appPrice": 0,
    "appScore": 4.5362,
    "appTitle": "Live 4D Results ! (MY & SG)",
    "revAuthor": "Zainudin Bujang",
    "revDate": "2017-12-03",
    "revRating": 5,
    "revText": "nk kena jackpot toto",
    "revTitle": "NA",
    "predicted": "Normal"
  },
  {
    "appId": "com.mobiusx.live4dresults",
    "appPrice": 0,
    "appScore": 4.5362,
    "appTitle": "Live 4D Results ! (MY & SG)",
    "revAuthor": "NA",
    "revDate": "2017-12-14",
    "revRating": 5,
    "revText": "saya amat berpuas hati",
    "revTitle": "NA",
    "predicted": "Normal"
  },
  {
    "appId": "com.mobiusx.live4dresults",
    "appPrice": 0,
    "appScore": 4.5362,
    "appTitle": "Live 4D Results ! (MY & SG)",
    "revAuthor": "Sufian Arshad",
    "revDate": "2017-11-18",
    "revRating": 5,
    "revText": "cepat dapat dan keputusan",
    "revTitle": "NA",
    "predicted": "Normal"
  },
  {
    "appId": "com.mobiusx.live4dresults",
    "appPrice": 0,
    "appScore": 4.5362,
    "appTitle": "Live 4D Results ! (MY & SG)",
    "revAuthor": "Wardiana Radi",
    "revDate": "2017-11-21",
    "revRating": 4,
    "revText": "tambah banyak mimpi saja",
    "revTitle": "NA",
    "predicted": "Normal"
  },
  {
    "appId": "com.mobiusx.live4dresults",
    "appPrice": 0,
    "appScore": 4.5362,
    "appTitle": "Live 4D Results ! (MY & SG)",
    "revAuthor": "Adam Adamboys",
    "revDate": "2017-11-07",
    "revRating": 5,
    "revText": "bagi saya nombor bertuah",
    "revTitle": "NA",
    "predicted": "Normal"
  },
  {
    "appId": "com.mobiusx.live4dresults",
    "appPrice": 0,
    "appScore": 4.5362,
    "appTitle": "Live 4D Results ! (MY & SG)",
    "revAuthor": "NA",
    "revDate": "2017-12-08",
    "revRating": 5,
    "revText": "semoga aku diberi rezeki",
    "revTitle": "NA",
    "predicted": "Normal"
  },
  {
    "appId": "com.mobiusx.live4dresults",
    "appPrice": 0,
    "appScore": 4.5362,
    "appTitle": "Live 4D Results ! (MY & SG)",
    "revAuthor": "NA",
    "revDate": "2017-10-25",
    "revRating": 5,
    "revText": "nombor terbaik saya nak",
    "revTitle": "NA",
    "predicted": "Normal"
  },
  {
    "appId": "com.mobiusx.live4dresults",
    "appPrice": 0,
    "appScore": 4.5362,
    "appTitle": "Live 4D Results ! (MY & SG)",
    "revAuthor": "Dausya9190 Dausya9190",
    "revDate": "2017-11-26",
    "revRating": 5,
    "revText": "memang bagus result ini",
    "revTitle": "NA",
    "predicted": "Normal"
  },
  {
    "appId": "com.mobiusx.live4dresults",
    "appPrice": 0,
    "appScore": 4.5362,
    "appTitle": "Live 4D Results ! (MY & SG)",
    "revAuthor": "NA",
    "revDate": "2018-01-05",
    "revRating": 5,
    "revText": "rinkas dan menyenang kan",
    "revTitle": "NA",
    "predicted": "Normal"
  },
  {
    "appId": "com.mobiusx.live4dresults",
    "appPrice": 0,
    "appScore": 4.5362,
    "appTitle": "Live 4D Results ! (MY & SG)",
    "revAuthor": "NA",
    "revDate": "2017-11-13",
    "revRating": 5,
    "revText": "best mudah tngok kputusan",
    "revTitle": "NA",
    "predicted": "Normal"
  },
  {
    "appId": "com.mobiusx.live4dresults",
    "appPrice": 0,
    "appScore": 4.5362,
    "appTitle": "Live 4D Results ! (MY & SG)",
    "revAuthor": "NA",
    "revDate": "2017-11-01",
    "revRating": 5,
    "revText": "mudah utk tgok keputusan👍",
    "revTitle": "NA",
    "predicted": "Normal"
  },
  {
    "appId": "com.mobiusx.live4dresults",
    "appPrice": 0,
    "appScore": 4.5362,
    "appTitle": "Live 4D Results ! (MY & SG)",
    "revAuthor": "NA",
    "revDate": "2017-12-10",
    "revRating": 5,
    "revText": "mmng terbaik keluaran nmr",
    "revTitle": "NA",
    "predicted": "Normal"
  },
  {
    "appId": "com.mobiusx.live4dresults",
    "appPrice": 0,
    "appScore": 4.5362,
    "appTitle": "Live 4D Results ! (MY & SG)",
    "revAuthor": "NA",
    "revDate": "2017-12-06",
    "revRating": 4,
    "revText": "memuaskan dan amat memudahkan",
    "revTitle": "NA",
    "predicted": "Normal"
  },
  {
    "appId": "com.mobiusx.live4dresults",
    "appPrice": 0,
    "appScore": 4.5362,
    "appTitle": "Live 4D Results ! (MY & SG)",
    "revAuthor": "NA",
    "revDate": "2017-10-22",
    "revRating": 4,
    "revText": "senang mau tgok ma mana tau kaya sudah mari kn kn",
    "revTitle": "NA",
    "predicted": "Normal"
  },
  {
    "appId": "com.mobiusx.live4dresults",
    "appPrice": 0,
    "appScore": 4.5362,
    "appTitle": "Live 4D Results ! (MY & SG)",
    "revAuthor": "ayi muda",
    "revDate": "2017-12-30",
    "revRating": 5,
    "revText": "puas hati tingok",
    "revTitle": "NA",
    "predicted": "Normal"
  },
  {
    "appId": "com.mobiusx.live4dresults",
    "appPrice": 0,
    "appScore": 4.5362,
    "appTitle": "Live 4D Results ! (MY & SG)",
    "revAuthor": "Nasir Acey",
    "revDate": "2017-12-01",
    "revRating": 1,
    "revText": "1st la kasi asik xkne je hmm",
    "revTitle": "NA",
    "predicted": "Normal"
  },
  {
    "appId": "com.mobiusx.live4dresults",
    "appPrice": 0,
    "appScore": 4.5362,
    "appTitle": "Live 4D Results ! (MY & SG)",
    "revAuthor": "NA",
    "revDate": "2017-12-01",
    "revRating": 5,
    "revText": "sebab no cepat dapat keputusan terbaik",
    "revTitle": "NA",
    "predicted": "Normal"
  },
  {
    "appId": "com.mobiusx.live4dresults",
    "appPrice": 0,
    "appScore": 4.5362,
    "appTitle": "Live 4D Results ! (MY & SG)",
    "revAuthor": "Anatasia Saweng",
    "revDate": "2017-12-24",
    "revRating": 5,
    "revText": "says sangat menyukainya walaupun tidak kena🙁🙁",
    "revTitle": "NA",
    "predicted": "Normal"
  },
  {
    "appId": "com.mobiusx.live4dresults",
    "appPrice": 0,
    "appScore": 4.5362,
    "appTitle": "Live 4D Results ! (MY & SG)",
    "revAuthor": "Al Dimar",
    "revDate": "2018-01-04",
    "revRating": 5,
    "revText": "terbaik bgi sya kenak thu",
    "revTitle": "NA",
    "predicted": "Normal"
  },
  {
    "appId": "com.mobiusx.live4dresults",
    "appPrice": 0,
    "appScore": 4.5362,
    "appTitle": "Live 4D Results ! (MY & SG)",
    "revAuthor": "Royston Temes",
    "revDate": "2017-12-30",
    "revRating": 5,
    "revText": "kasih no 9194 keluar slalu",
    "revTitle": "NA",
    "predicted": "Normal"
  },
  {
    "appId": "com.mobiusx.live4dresults",
    "appPrice": 0,
    "appScore": 4.5362,
    "appTitle": "Live 4D Results ! (MY & SG)",
    "revAuthor": "Suwandi Boy",
    "revDate": "2017-10-25",
    "revRating": 5,
    "revText": "kena makan trus kasian nasib",
    "revTitle": "NA",
    "predicted": "Normal"
  },
  {
    "appId": "com.mobiusx.live4dresults",
    "appPrice": 0,
    "appScore": 4.5362,
    "appTitle": "Live 4D Results ! (MY & SG)",
    "revAuthor": "Petrus Julius",
    "revDate": "2017-10-28",
    "revRating": 5,
    "revText": "4d results senang nak urus",
    "revTitle": "NA",
    "predicted": "Normal"
  },
  {
    "appId": "com.mobiusx.live4dresults",
    "appPrice": 0,
    "appScore": 4.5362,
    "appTitle": "Live 4D Results ! (MY & SG)",
    "revAuthor": "NA",
    "revDate": "2017-10-30",
    "revRating": 5,
    "revText": "terbaik dan mudah mendapat keputusan",
    "revTitle": "NA",
    "predicted": "Normal"
  },
  {
    "appId": "com.mobiusx.live4dresults",
    "appPrice": 0,
    "appScore": 4.5362,
    "appTitle": "Live 4D Results ! (MY & SG)",
    "revAuthor": "Azri Azri",
    "revDate": "2017-12-09",
    "revRating": 5,
    "revText": "mmg bgus ley cpt kaya",
    "revTitle": "NA",
    "predicted": "Normal"
  },
  {
    "appId": "com.mobiusx.live4dresults",
    "appPrice": 0,
    "appScore": 4.5362,
    "appTitle": "Live 4D Results ! (MY & SG)",
    "revAuthor": "Azhar Aan45",
    "revDate": "2017-10-31",
    "revRating": 5,
    "revText": "kena a1 damacai terbaik laa",
    "revTitle": "NA",
    "predicted": "Normal"
  },
  {
    "appId": "com.mobiusx.live4dresults",
    "appPrice": 0,
    "appScore": 4.5362,
    "appTitle": "Live 4D Results ! (MY & SG)",
    "revAuthor": "NA",
    "revDate": "2017-11-25",
    "revRating": 5,
    "revText": "harap2 nak kena besar je",
    "revTitle": "NA",
    "predicted": "Normal"
  },
  {
    "appId": "com.mobiusx.live4dresults",
    "appPrice": 0,
    "appScore": 4.5362,
    "appTitle": "Live 4D Results ! (MY & SG)",
    "revAuthor": "Zurina Seman",
    "revDate": "2017-11-14",
    "revRating": 5,
    "revText": "8484 kasi keluar esok 1st",
    "revTitle": "NA",
    "predicted": "Normal"
  },
  {
    "appId": "com.mobiusx.live4dresults",
    "appPrice": 0,
    "appScore": 4.5362,
    "appTitle": "Live 4D Results ! (MY & SG)",
    "revAuthor": "NA",
    "revDate": "2017-11-25",
    "revRating": 5,
    "revText": "ok bah tak penat mencari keputusan 4d",
    "revTitle": "NA",
    "predicted": "Normal"
  },
  {
    "appId": "com.mobiusx.live4dresults",
    "appPrice": 0,
    "appScore": 4.5362,
    "appTitle": "Live 4D Results ! (MY & SG)",
    "revAuthor": "Hary Pansiang",
    "revDate": "2017-11-06",
    "revRating": 5,
    "revText": "ok juga tp tak penah kene",
    "revTitle": "NA",
    "predicted": "Normal"
  },
  {
    "appId": "com.mobiusx.live4dresults",
    "appPrice": 0,
    "appScore": 4.5362,
    "appTitle": "Live 4D Results ! (MY & SG)",
    "revAuthor": "# Darren Lee",
    "revDate": "2017-11-25",
    "revRating": 5,
    "revText": "maklumat yg d beri sepadan dgn keinginan",
    "revTitle": "NA",
    "predicted": "Normal"
  },
  {
    "appId": "com.mobiusx.live4dresults",
    "appPrice": 0,
    "appScore": 4.5362,
    "appTitle": "Live 4D Results ! (MY & SG)",
    "revAuthor": "Jamal Soul",
    "revDate": "2017-11-04",
    "revRating": 5,
    "revText": "i like  hahaha",
    "revTitle": "NA",
    "predicted": "Normal"
  },
  {
    "appId": "com.mobiusx.live4dresults",
    "appPrice": 0,
    "appScore": 4.5362,
    "appTitle": "Live 4D Results ! (MY & SG)",
    "revAuthor": "Acik Achik",
    "revDate": "2017-12-03",
    "revRating": 5,
    "revText": "special draw date letak sekali laa",
    "revTitle": "NA",
    "predicted": "Normal"
  },
  {
    "appId": "com.mobiusx.live4dresults",
    "appPrice": 0,
    "appScore": 4.5362,
    "appTitle": "Live 4D Results ! (MY & SG)",
    "revAuthor": "NA",
    "revDate": "2017-12-02",
    "revRating": 5,
    "revText": "harapan aku no 1 sama no 3",
    "revTitle": "NA",
    "predicted": "Normal"
  },
  {
    "appId": "com.mobiusx.live4dresults",
    "appPrice": 0,
    "appScore": 4.5362,
    "appTitle": "Live 4D Results ! (MY & SG)",
    "revAuthor": "Juad Madif",
    "revDate": "2017-12-05",
    "revRating": 5,
    "revText": "4d ni sngt bgus la blh la sy liht di sini tk paya la  ssh kn",
    "revTitle": "NA",
    "predicted": "Normal"
  },
  {
    "appId": "com.mobiusx.live4dresults",
    "appPrice": 0,
    "appScore": 4.5362,
    "appTitle": "Live 4D Results ! (MY & SG)",
    "revAuthor": "sri mulyati",
    "revDate": "2017-12-06",
    "revRating": 3,
    "revText": "kasi la nomor mimpi yg jitu",
    "revTitle": "NA",
    "predicted": "Spam"
  },
  {
    "appId": "com.mobiusx.live4dresults",
    "appPrice": 0,
    "appScore": 4.5362,
    "appTitle": "Live 4D Results ! (MY & SG)",
    "revAuthor": "Abdul Malik MD RAPAI",
    "revDate": "2017-11-14",
    "revRating": 5,
    "revText": "kena buat carta untuk cai pulak",
    "revTitle": "NA",
    "predicted": "Normal"
  },
  {
    "appId": "com.mobiusx.live4dresults",
    "appPrice": 0,
    "appScore": 4.5362,
    "appTitle": "Live 4D Results ! (MY & SG)",
    "revAuthor": "NA",
    "revDate": "2017-12-11",
    "revRating": 5,
    "revText": "best yo  bila la nk naik no 1 no2 no 3",
    "revTitle": "NA",
    "predicted": "Normal"
  },
  {
    "appId": "com.mobiusx.live4dresults",
    "appPrice": 0,
    "appScore": 4.5362,
    "appTitle": "Live 4D Results ! (MY & SG)",
    "revAuthor": "POWER OF LOVE1995",
    "revDate": "2017-12-03",
    "revRating": 5,
    "revText": "boleh la slalu kna hari bulan lol",
    "revTitle": "NA",
    "predicted": "Normal"
  }
]
